{
    "constructors": [],
    "externalReferences": [],
    "id": "01p50000003rxhKAAQ",
    "innerClasses": [],
    "interfaces": [],
    "key": "01p50000003rxhKAAQ",
    "methods": [
        {
            "annotations": [
                {
                    "name": "TestSetup"
                }
            ],
            "location": {
                "column": 17,
                "line": 4
            },
            "modifiers": [
                "private",
                "static"
            ],
            "name": "testDataSetup",
            "parameters": [],
            "references": [],
            "returnType": "void",
            "type": null
        },
        {
            "annotations": [
                {
                    "name": "IsTest"
                }
            ],
            "location": {
                "column": 17,
                "line": 23
            },
            "modifiers": [
                "private",
                "static",
                "testMethod"
            ],
            "name": "testGetAccounts",
            "parameters": [],
            "references": [],
            "returnType": "void",
            "type": null
        },
        {
            "annotations": [
                {
                    "name": "IsTest"
                }
            ],
            "location": {
                "column": 17,
                "line": 50
            },
            "modifiers": [
                "private",
                "static",
                "testMethod"
            ],
            "name": "testgetFailRecords",
            "parameters": [],
            "references": [],
            "returnType": "void",
            "type": null
        },
        {
            "annotations": [
                {
                    "name": "IsTest"
                }
            ],
            "location": {
                "column": 17,
                "line": 76
            },
            "modifiers": [
                "private",
                "static",
                "testMethod"
            ],
            "name": "testGetOneAccount",
            "parameters": [],
            "references": [],
            "returnType": "void",
            "type": null
        },
        {
            "annotations": [
                {
                    "name": "IsTest"
                }
            ],
            "location": {
                "column": 17,
                "line": 95
            },
            "modifiers": [
                "private",
                "static",
                "testMethod"
            ],
            "name": "testGetOneFailAccount",
            "parameters": [],
            "references": [],
            "returnType": "void",
            "type": null
        },
        {
            "annotations": [
                {
                    "name": "IsTest"
                }
            ],
            "location": {
                "column": 17,
                "line": 112
            },
            "modifiers": [
                "private",
                "static",
                "testMethod"
            ],
            "name": "testCreateAccount",
            "parameters": [],
            "references": [],
            "returnType": "void",
            "type": null
        },
        {
            "annotations": [
                {
                    "name": "IsTest"
                }
            ],
            "location": {
                "column": 17,
                "line": 133
            },
            "modifiers": [
                "private",
                "static",
                "testMethod"
            ],
            "name": "testCreateAvailableAccount",
            "parameters": [],
            "references": [],
            "returnType": "void",
            "type": null
        },
        {
            "annotations": [
                {
                    "name": "IsTest"
                }
            ],
            "location": {
                "column": 17,
                "line": 154
            },
            "modifiers": [
                "private",
                "static",
                "testMethod"
            ],
            "name": "testFailCreateAccount",
            "parameters": [],
            "references": [],
            "returnType": "void",
            "type": null
        }
    ],
    "name": "APIManagerTest",
    "namespace": null,
    "parentClass": "",
    "properties": [],
    "tableDeclaration": {
        "annotations": [
            {
                "name": "IsTest"
            }
        ],
        "location": {
            "column": 14,
            "line": 2
        },
        "modifiers": [
            "public",
            "testMethod"
        ],
        "name": "APIManagerTest",
        "references": [],
        "type": "APIManagerTest"
    },
    "variables": [
        {
            "annotations": [],
            "location": {
                "column": 23,
                "line": 6
            },
            "modifiers": [],
            "name": "accList",
            "references": [],
            "type": "LIST"
        },
        {
            "annotations": [],
            "location": {
                "column": 21,
                "line": 7
            },
            "modifiers": [],
            "name": "i",
            "references": [],
            "type": "Integer"
        },
        {
            "annotations": [],
            "location": {
                "column": 29,
                "line": 15
            },
            "modifiers": [],
            "name": "jsonObj",
            "references": [],
            "type": "LIST"
        },
        {
            "annotations": [],
            "location": {
                "column": 21,
                "line": 25
            },
            "modifiers": [],
            "name": "request",
            "references": [],
            "type": "RestRequest"
        },
        {
            "annotations": [],
            "location": {
                "column": 40,
                "line": 42
            },
            "modifiers": [],
            "name": "response",
            "references": [],
            "type": "RestResponseHandler"
        },
        {
            "annotations": [],
            "location": {
                "column": 21,
                "line": 52
            },
            "modifiers": [],
            "name": "request",
            "references": [],
            "type": "RestRequest"
        },
        {
            "annotations": [],
            "location": {
                "column": 40,
                "line": 69
            },
            "modifiers": [],
            "name": "response",
            "references": [],
            "type": "RestResponseHandler"
        },
        {
            "annotations": [],
            "location": {
                "column": 17,
                "line": 78
            },
            "modifiers": [],
            "name": "a",
            "references": [],
            "type": "Account"
        },
        {
            "annotations": [],
            "location": {
                "column": 21,
                "line": 81
            },
            "modifiers": [],
            "name": "request",
            "references": [],
            "type": "RestRequest"
        },
        {
            "annotations": [],
            "location": {
                "column": 40,
                "line": 89
            },
            "modifiers": [],
            "name": "response",
            "references": [],
            "type": "RestResponseHandler"
        },
        {
            "annotations": [],
            "location": {
                "column": 21,
                "line": 98
            },
            "modifiers": [],
            "name": "request",
            "references": [],
            "type": "RestRequest"
        },
        {
            "annotations": [],
            "location": {
                "column": 40,
                "line": 106
            },
            "modifiers": [],
            "name": "response",
            "references": [],
            "type": "RestResponseHandler"
        },
        {
            "annotations": [],
            "location": {
                "column": 21,
                "line": 115
            },
            "modifiers": [],
            "name": "request",
            "references": [],
            "type": "RestRequest"
        },
        {
            "annotations": [],
            "location": {
                "column": 40,
                "line": 125
            },
            "modifiers": [],
            "name": "response",
            "references": [],
            "type": "RestResponseHandler"
        },
        {
            "annotations": [],
            "location": {
                "column": 21,
                "line": 136
            },
            "modifiers": [],
            "name": "request",
            "references": [],
            "type": "RestRequest"
        },
        {
            "annotations": [],
            "location": {
                "column": 40,
                "line": 146
            },
            "modifiers": [],
            "name": "response",
            "references": [],
            "type": "RestResponseHandler"
        },
        {
            "annotations": [],
            "location": {
                "column": 21,
                "line": 157
            },
            "modifiers": [],
            "name": "request",
            "references": [],
            "type": "RestRequest"
        },
        {
            "annotations": [],
            "location": {
                "column": 40,
                "line": 167
            },
            "modifiers": [],
            "name": "response",
            "references": [],
            "type": "RestResponseHandler"
        }
    ]
}